email_client/__init__.py
email_client/server.py
email_client_mcp_server-0.1.0.dist-info/licenses/LICENSE
email_client_mcp_server-0.1.0.dist-info/METADATA
email_client_mcp_server-0.1.0.dist-info/WHEEL
email_client_mcp_server-0.1.0.dist-info/entry_points.txt
email_client_mcp_server-0.1.0.dist-info/top_level.txt
email_client_mcp_server-0.1.0.dist-info/RECORD
