Metadata-Version: 2.4
Name: email-client-mcp-server
Version: 0.1.0
Summary: Email search and management tool using MCP protocol
Requires-Python: >=3.11
License-File: LICENSE
Requires-Dist: asyncio>=3.4.3
Requires-Dist: httpx>=0.28.1
Requires-Dist: mcp>=1.5.0
Requires-Dist: python-dotenv>=1.1.0
Dynamic: license-file
